README.md
setup.py
zhei/__init__.py
zhei/intro.py
zheizhei.egg-info/PKG-INFO
zheizhei.egg-info/SOURCES.txt
zheizhei.egg-info/dependency_links.txt
zheizhei.egg-info/requires.txt
zheizhei.egg-info/top_level.txt