Metadata-Version: 2.1
Name: zheizhei
Version: 0.0.10
Summary: Deep learning tools
Home-page: https://github.com/deng1fan
Author: deng1fan
Author-email: dengyifan@iie.ac.cn
Keywords: zhei,deep learning,pytorch
Requires-Python: >=3.6
